w3c_nu_validator-0.1.1.dist-info/licenses/LICENSE
w3c_validator/__init__.py
w3c_validator/cli.py
w3c_nu_validator-0.1.1.dist-info/METADATA
w3c_nu_validator-0.1.1.dist-info/WHEEL
w3c_nu_validator-0.1.1.dist-info/entry_points.txt
w3c_nu_validator-0.1.1.dist-info/top_level.txt
w3c_nu_validator-0.1.1.dist-info/RECORD
