Metadata-Version: 2.4
Name: w3c-nu-validator
Version: 0.1.1
Summary: CLI tool to validate deployed URLs via the W3C Nu HTML Checker (JSON output).
Author: Rob Shelford
License: MIT License
Project-URL: Homepage, https://github.com/yenmangu/w3c-validator
Project-URL: Repository, https://github.com/yenmangu/w3c-validator
Project-URL: Issues, https://github.com/yenmangu/w3c-validator/issues
Keywords: w3c,html,validator,nu,accessibility,testing
Classifier: Development Status :: 3 - Alpha
Classifier: Environment :: Console
Classifier: Intended Audience :: Developers
Classifier: License :: OSI Approved :: MIT License
Classifier: Programming Language :: Python :: 3
Classifier: Programming Language :: Python :: 3 :: Only
Classifier: Programming Language :: Python :: 3.10
Classifier: Programming Language :: Python :: 3.11
Classifier: Programming Language :: Python :: 3.12
Classifier: Programming Language :: Python :: 3.13
Classifier: Topic :: Internet :: WWW/HTTP
Classifier: Topic :: Software Development :: Testing
Classifier: Topic :: Text Processing :: Markup :: HTML
Requires-Python: >=3.10
License-File: LICENSE
Requires-Dist: requests
Dynamic: license-file
